batlab/__init__.py
batlab/batlabclass/BatlabClass.py
batlab/batlabclass/__init__.py
batlab/batlabutil/__init__.py
batlab/batlabutil/batlabutil.py
batlab/batpool/Batpool.py
batlab/batpool/__init__.py
batlab/channel/Channel.py
batlab/channel/__init__.py
batlab/constants/__init__.py
batlab/constants/constants.py
batlab/encoder/Encoder.py
batlab/encoder/__init__.py
batlab/func/__init__.py
batlab/func/func.py
batlab/logger/Logger.py
batlab/logger/__init__.py
batlab/packet/Packet.py
batlab/packet/__init__.py
batlab/settings/Settings.py
batlab/settings/__init__.py
batlab-0.5.36.dist-info/LICENSE
batlab-0.5.36.dist-info/METADATA
batlab-0.5.36.dist-info/WHEEL
batlab-0.5.36.dist-info/entry_points.txt
batlab-0.5.36.dist-info/top_level.txt
batlab-0.5.36.dist-info/RECORD
