Metadata-Version: 2.1
Name: batlab
Version: 0.5.36
Summary: Low level library for communication with the Batlab V1.0 Battery Testing System by Lexcelon
Home-page: https://github.com/Lexcelon/batlab-software-python
Author: Lexcelon, LLC
Author-email: support@lexcelon.com
License: LGPL3
Platform: UNKNOWN
Requires-Dist: pyserial
Requires-Dist: future
